{"titulo":"Biografia não autorizada de minha Avó","autor":"Eduardo Azevedo","descricao":"Uma biografia sci-fi rural em quadrinhos.","municipio":"Campo Grande","uf":"MS","situacao":"financiado","porcentagem":1.518,"encerramento":"17/04/2020","ano":"2020","apoiadores":55,"modalidade":"flex","valorLevantado":2277,"meta":1500,"novidades":6,"recompensas":9,"mencaoCcxp":"N","mencaoPolitica":"N","mencaoEconomia":"N","mencaoLgbt":"N","mencaoFeminismo":"N","mencaoQuestoesDeGenero":"N","mencaoReligiao":"N","mencaoHeroi":"N","mencaoHumor":"N","mencaoBiografia":"S","mencaoManga":"N","mencaoZine":"S","apresentacao":"O projeto No futuro, presente ou passado. Minha Avó nasceu, como um dos primeiros humanos nativamente marcianos, que de nada diferiam dos terráqueos: trabalhavam e descansavam, amavam e sofriam. Com exceção, é claro, de que deveriam usar seus capacetes de respiração.\n\n\n\nOlá, sou Eduardo Azevedo. Cartunista campo-grandense, desenho desde que me conheço por gente. Mas, essa habilidade veio tomar conta de minha vida nos últimos dois anos, quando comecei a divulgar meus rabiscos, e disso surgiram vários projetos legais.\n\nBiografia não autorizada de minha Avó (que viveu em Marte.) é meu primeiro quadrinho autoral, e o resultado de todo esse processo.\n\n\n\nBaseado na vida de minha avó e escrito com a ajuda do querido João Gabriel Benitez. Esse sci-fi rural é uma biografia não autorizada, pois minha avó pediu que mudasse os nomes dos personagens e o contexto dos acontecimentos para que ninguém soubesse que a história era dela.\n\nAcabei mudando até o nome do planeta.\n\n\n\nCom 48 páginas, divididas em 3 capítulos, a história reflete toda as avós que cresceram em um Brasil rural, que foram empregadas domésticas, que moraram em terras arrendadas, que se apaixonaram e sofreram e que por fim construíram uma família. Espero que ela fale com os netos dessas avós.\n\n\n\nComo vai funcionar a campanha?\n\nVou usar essa campanha do Catarse como pré-venda da hq. Aqui você pode ajudar nos meus custos de impressão, garantir a sua cópia, e ainda descolar uns produtos exclusivos. Essa “pré venda x capitação” de recursos ocorrerá entre os meses de Fevereiro, Março, até meados de Abril.\n\nAbaixo seguem as recompensas que vocês podem adquirir nos pacotes ao lado ajudando esse projeto.\n\n\n\nComo a impressão será feita após o fim da campanha, com um estimativa de 30 dias somando orçamentos, produção e entrega das cópias da hq, as recompensas deverão ser entregues em meados de Maio.\n\nO frete para Campo Grande MS é Grátis!\n\nEspero que aproveitem os pacotes, e mais importante, que gostem da hq!\n\nEsse é um projeto pessoal com muito carinho envolvido.\n\nObrigado desde já!\n\n\n\nVocê pode saber mais sobre o meu trabalho acompanhando as minhas redes e o meu site. Cheque também a exposição que gerou o zine \"Ninguém precisa de um arquiteto.\" que é uma das recompensas oferecidas.\n\n\nOrçamento\nDenunciar este projeto ao Catarse","recAte30":2,"recAte60":3,"recAte90":1,"rec90Mais":3,"apoioAte30":28,"apoioAte60":20,"apoioAte90":3,"apoio90Mais":4,"regiao":"centro-oeste","url":"https://catarse.me/biografianaoautorizada"}