{"titulo":"Hungry Snacks, Os Salgaditos!","autor":"Noé da Matta Ribeiro","descricao":"Alimente Seus Sonhos! Hungry Snacks, Os Salgaditos!","municipio":"Vitória","uf":"ES","situacao":"não financiado","porcentagem":0,"encerramento":"18/05/2018","ano":"2018","apoiadores":0,"modalidade":"flex","valorLevantado":0,"meta":10778.330293263094,"novidades":4,"recompensas":3,"mencaoCcxp":"N","mencaoPolitica":"N","mencaoEconomia":"N","mencaoLgbt":"N","mencaoFeminismo":"N","mencaoQuestoesDeGenero":"N","mencaoReligiao":"N","mencaoHeroi":"N","mencaoHumor":"N","mencaoBiografia":"N","mencaoManga":"N","mencaoZine":"N","apresentacao":"O projeto O que é HUNGRY SNACKS, Os Salgaditos?\n\nÉ uma história em quadrinhos voltada para o público infanto-juvenil sobre um grupo de amigos (Os Salgaditos) que vive na Padaria Paraíso e tem seu livro de receitas furtado por um Chef inescrupuloso.Coxinha, Quibão, Enroladinho, Pão de Queijo e Pastel Chinês decidem então recuperar o livro, que tem a capacidade de criar novos salgadinhos. Mas para isso, terão que enfrentar o Chef Nariz de Coxinha, sua colher mágica e o próprio livro de receitas.\n\n\n\nPor que apoiar HUNGRY SNACKS, Os Salgaditos?\n\nApoiar nosso projeto é apoiar um material leve e divertido para crianças e adolescentes, visando estimular a imaginação e apresentar novos e encantadores personagens inspirados na nossa culinária tradicional.\nOrçamentoTendo em vista o ideal de confeccionar 2000 revistas.\n\n20% para Recompensas\n\n40% para Produção da HQ\n\n25% para Divulgação e Marketing\n\n15% para o Autor\nDenunciar este projeto ao Catarse","recAte30":2,"recAte60":0,"recAte90":0,"rec90Mais":1,"apoioAte30":0,"apoioAte60":0,"apoioAte90":0,"apoio90Mais":0,"regiao":"sudeste","url":"https://catarse.me/hungry_snacks_os_salgaditos_975e"}