{"titulo":"JÁ ERA","autor":"Felipe Parucci","descricao":"JÁ ERA é uma DRAMÉDIA PSICODÉLICA em quadrinhos que retrata uma tentativa de fuga da realidade","municipio":"Florianópolis","uf":"SC","situacao":"financiado","porcentagem":1.0719200000000002,"encerramento":"09/10/2016","ano":"2016","apoiadores":301,"modalidade":"tudo ou nada","valorLevantado":30247.127223114236,"meta":28217.709552125376,"novidades":9,"recompensas":14,"mencaoCcxp":"S","mencaoPolitica":"N","mencaoEconomia":"N","mencaoLgbt":"N","mencaoFeminismo":"N","mencaoQuestoesDeGenero":"N","mencaoReligiao":"N","mencaoHeroi":"N","mencaoHumor":"N","mencaoBiografia":"N","mencaoManga":"N","mencaoZine":"S","apresentacao":"O projetoO marasmo, a mesmice, a rotina, os preconceitos, as inseguranças, as ironias, o tédio, o ódio, a inveja, as crenças, as substâncias, as mentiras, o medo, a discórdia, os arrependimentos, as teorias, as incertezas, o pânico, o tempo, a humanidade: JÁ ERA!!JÁ ERA é uma DRAMÉDIA PSICODÉLICA que conta a história de Regina, uma publicitária que trabalha muito, mas ganha pouco. Suas interações sociais são extremamente tediosas e vive em um mundo repleto de PIRAS ERRADAS. Cansada de seu cotidiano decepcionante e com um empurrãozinho do destino, ela vê a oportunidade de comprar um barco e sair navegando sem rumo, em busca de uma razão de existir. Entretanto, as ondas do destino acabam levando Regina para uma VIAGEM SURREAL, e ela encontra a oportunidade de mudar o nosso mundo. Ou só o mundo dela?Felipe Parucci é quadrinista autor de Apocalipse, por favor, HQ lançada de forma independente, aclamada pela crítica e indicada ao prêmio Troféu HQMIX 2016 nas categorias Novo Talento Roteirista e Publicação Independente - Edição Única.  JÁ ERA é o segundo livro a ser produzido pelo autor. Esse projeto busca financiar sua publicação impressa. O livro terá aproximadamente 300 páginas (como o projeto está em andamento, ainda não é possível delimitar o numero exato) com roteiro, arte, diagramação, revisão e edição feitas pelo próprio Felipe.Pra saber mais sobre o projeto e o livro: https://www.facebook.com/jaerahq/Pra trocar uma ideia com o autor: https://www.facebook.com/felipe.parucciPra curiosidades, sketchs e imagens maneiras: https://www.instagram.com/felipeparucci/Sobre o primeiro livro do Felipe, Apocalipse, por favor: https://www.facebook.com/apocalipseporfavor/Além do livro, é possível adquirir várias recompensas produzidas com muito carinho pelo Felipe. Tem prints em tamanho A3 e A2, caneca, estatueta, quadros, etc. Ao longo da campanha, vamos divulgar algumas dessas recompensas com mais detalhes.Até agora, divulguei:Poster A3: https://www.facebook.com/jaerahq/posts/62258098125...Poster A2 grandão bonitasso: http://bit.ly/2brwzG5Caneca fabulosa: http://bit.ly/2bCRAtQPintura em tela: https://www.facebook.com/jaerahq/photos/a.55211267...Zine Auto Ajuda: https://www.facebook.com/jaerahq/posts/62485464102...Abaixo, algumas páginas pra dar um gostinho (sem spoilers!). Durante a campanha, mais páginas serão mostradas. Não se esqueça de curtir a fanpage (ali nos links) pra acompanhar a produção da HQ!!!OrçamentoA meta mínima pra produção do livro é de R$ 25.000,00. Esse valor inclui a impressão do livro, a taxa do catarse, as taxas de envio e a produção das recompensas. A previsão de envio das recompensas e do livro é Abril de 2017. Curtiu? Apoie! Compartilhe! Ajude a contar essa história! (:Denunciar este projeto ao Catarse","recAte30":4,"recAte60":4,"recAte90":6,"rec90Mais":14,"apoioAte30":10,"apoioAte60":116,"apoioAte90":73,"apoio90Mais":70,"regiao":"sul","url":"https://catarse.me/jaera"}